adk_sim_protos/__init__.py
adk_sim_protos/adksim/__init__.py
adk_sim_protos/adksim/v1/__init__.py
adk_sim_protos/google/__init__.py
adk_sim_protos/google/ai/__init__.py
adk_sim_protos/google/ai/generativelanguage/__init__.py
adk_sim_protos/google/ai/generativelanguage/v1beta/__init__.py
adk_sim_protos/google/api/__init__.py
adk_sim_protos/google/type/__init__.py
adk_sim_protos_patch/__init__.py
adk_sim_protos-0.1.22.dist-info/METADATA
adk_sim_protos-0.1.22.dist-info/WHEEL
adk_sim_protos-0.1.22.dist-info/RECORD
