Metadata-Version: 2.4
Name: adk-sim-protos
Version: 0.1.22
Summary: Generated Protocol Buffers for ADK Simulator
Requires-Python: >=3.14
Requires-Dist: betterproto>=2.0.0b7
Requires-Dist: google-ai-generativelanguage>=0.9.0
